brixs/__init__.py
brixs/brixs.py
brixs/config.py
brixs/addons/__init__.py
brixs/addons/broaden.py
brixs/addons/centroid.py
brixs/addons/experimental.py
brixs/addons/finder(safecopy).py
brixs/addons/finder.py
brixs/addons/fitting.py
brixs/addons/h5.py
brixs/addons/labels.py
brixs/addons/pdfmanip.py
brixs/addons/png2clipboard.py
brixs/addons/sendemail.py
brixs/addons/sound.py
brixs/addons/spec.py
brixs/addons/svgmanip.py
brixs/backpack/__init__.py
brixs/backpack/arraymanip.py
brixs/backpack/figmanip.py
brixs/backpack/filemanip.py
brixs/backpack/numanip.py
brixs/backpack/other.py
brixs/backpack/vectormanip.py
brixs/beamlines/adress/__init__.py
brixs/beamlines/adress/adress(obsolete).py
brixs/beamlines/i21/__init__.py
brixs/beamlines/i21/advanced.py
brixs/beamlines/i21/core.py
brixs/beamlines/i21/template.py
brixs/beamlines/i21/obsolete/i21.py
brixs/beamlines/id32/__init__.py
brixs/beamlines/id32/advanced.py
brixs/beamlines/id32/core.py
brixs/beamlines/id32/core_obsolete.py
brixs/beamlines/ipe/__init__.py
brixs/beamlines/ipe/advanced.py
brixs/beamlines/ipe/core.py
brixs/beamlines/ipe/experimental.py
brixs/beamlines/ipe/ipeods.py
brixs/beamlines/ipe/obsolete/IPE_old.py
brixs/beamlines/ipe/obsolete/ipe.py
brixs/beamlines/ipe/quickviewer/ascan.py
brixs/beamlines/ipe/quickviewer/back.png
brixs/beamlines/ipe/quickviewer/default.py
brixs/beamlines/ipe/quickviewer/folder.png
brixs/beamlines/ipe/quickviewer/update.png
brixs/beamlines/ipe/quickviewer/xas.py
brixs/beamlines/peaxis/PEAXIS(possibly obsolete).py
brixs/beamlines/scs/__init__.py
brixs/beamlines/scs/scs_obsolete.py
brixs/beamlines/veritas/VERITASods.py
brixs/beamlines/veritas/VERITASold.py
brixs/beamlines/veritas/__init__.py
brixs/beamlines/veritas/advanced.py
brixs/beamlines/veritas/core.py
brixs/beamlines/veritas/experimental.py
brixs/crystal/__init__.py
brixs/crystal/crystal.py
brixs/model/__init__.py
brixs/model/model(safe).py
brixs/model/model.py
brixs/model/model_functions.py
brixs/model/peaks.py
brixs-0.1.1.dist-info/METADATA
brixs-0.1.1.dist-info/WHEEL
brixs-0.1.1.dist-info/licenses/LICENSE
brixs-0.1.1.dist-info/RECORD
