Metadata-Version: 2.4
Name: brixs
Version: 0.1.1
Summary: An object-oriented Python package for processing and analyzing RIXS and XAS experimental data, designed to be user-friendly and efficient for scientific research.
Author-email: Carlos William Galdino <carlos.galdino@psi.ch>, Thiago Mori <thiago.mori@lnls.br>, Felipe Custodio <felipe.custodio@lnls.br>, Tulio Rocha <tulio.rocha@lnls.br>
Maintainer-email: Carlos William Galdino <carlos.galdino@psi.ch>, Felipe Custodio <felipe.custodio@lnls.br>
License: MIT License
License-File: LICENSE
Keywords: RIXS,Synchrotron,X-ray,XAS,beamline
Classifier: License :: OSI Approved :: MIT License
Classifier: Operating System :: OS Independent
Classifier: Programming Language :: Python :: 3
Requires-Python: >=3.10
Requires-Dist: matplotlib>=3.10
Requires-Dist: numpy>=1.15
